LearnVersionControlWithGitZhongwenban/README.md
LearnVersionControlWithGitZhongwenban/__init__.py
LearnVersionControlWithGitZhongwenban/__main__.py
LearnVersionControlWithGitZhongwenban/file.epub
LearnVersionControlWithGitZhongwenban/index.html
LearnVersionControlWithGitZhongwenban/css/__init__.py
LearnVersionControlWithGitZhongwenban/css/annotations.css
LearnVersionControlWithGitZhongwenban/css/main.css
LearnVersionControlWithGitZhongwenban/css/normalize.css
LearnVersionControlWithGitZhongwenban/css/popup.css
LearnVersionControlWithGitZhongwenban/font/__init__.py
LearnVersionControlWithGitZhongwenban/font/fontello.eot
LearnVersionControlWithGitZhongwenban/font/fontello.svg
LearnVersionControlWithGitZhongwenban/font/fontello.ttf
LearnVersionControlWithGitZhongwenban/font/fontello.woff
LearnVersionControlWithGitZhongwenban/img/__init__.py
LearnVersionControlWithGitZhongwenban/img/annotator-glyph-sprite.png
LearnVersionControlWithGitZhongwenban/img/annotator-icon-sprite.png
LearnVersionControlWithGitZhongwenban/img/apple-touch-icon.png
LearnVersionControlWithGitZhongwenban/img/cancelfullscreen.png
LearnVersionControlWithGitZhongwenban/img/close.png
LearnVersionControlWithGitZhongwenban/img/fullscreen.png
LearnVersionControlWithGitZhongwenban/img/loader.gif
LearnVersionControlWithGitZhongwenban/img/menu-icon.png
LearnVersionControlWithGitZhongwenban/img/save.png
LearnVersionControlWithGitZhongwenban/img/saved.png
LearnVersionControlWithGitZhongwenban/img/settings-s.png
LearnVersionControlWithGitZhongwenban/img/settings.png
LearnVersionControlWithGitZhongwenban/img/star.png
LearnVersionControlWithGitZhongwenban/js/__init__.py
LearnVersionControlWithGitZhongwenban/js/epub.js
LearnVersionControlWithGitZhongwenban/js/epub.min.js
LearnVersionControlWithGitZhongwenban/js/epub.min.map
LearnVersionControlWithGitZhongwenban/js/hooks.min.js
LearnVersionControlWithGitZhongwenban/js/hooks.min.map
LearnVersionControlWithGitZhongwenban/js/reader.js
learn_version_control_with_git_zhongwenban-2024.3.1.0.dist-info/METADATA
learn_version_control_with_git_zhongwenban-2024.3.1.0.dist-info/WHEEL
learn_version_control_with_git_zhongwenban-2024.3.1.0.dist-info/entry_points.txt
learn_version_control_with_git_zhongwenban-2024.3.1.0.dist-info/top_level.txt
learn_version_control_with_git_zhongwenban-2024.3.1.0.dist-info/RECORD
